[{"name":"ObtenerDatosApostille","nameKey":"2.6","imports":["3.8"]},{"name":"ObtenerDatosdeDictamen","nameKey":"3.7","imports":["3.8"]},{"name":"ObtenerDatosEstadoCivil","nameKey":"3.8","imports":["3.9","3.7","3.10","2.6","5.15"]},{"name":"ObtenerDatosPartida","nameKey":"3.9","imports":["3.8"]},{"name":"ObtenerInfSumariaDecJurada","nameKey":"3.10","imports":["3.8"]},{"name":"RealizaReversion","nameKey":"3.11","imports":[]},{"name":"ListarPersxDoc","nameKey":"3.12","imports":[]},{"name":"ObtenerPersonaxCUIL","nameKey":"4.13","imports":["4.14"]},{"name":"ObtenerPersonaxCUIP","nameKey":"4.14","imports":["4.13"]},{"name":"ObtenerDatosdeSentencia","nameKey":"5.15","imports":["3.8"]}]
